mbed_tools/__init__.py
mbed_tools/build/__init__.py
mbed_tools/build/build.py
mbed_tools/build/config.py
mbed_tools/build/exceptions.py
mbed_tools/build/flash.py
mbed_tools/build/_internal/__init__.py
mbed_tools/build/_internal/cmake_file.py
mbed_tools/build/_internal/find_files.py
mbed_tools/build/_internal/write_files.py
mbed_tools/build/_internal/config/__init__.py
mbed_tools/build/_internal/config/assemble_build_config.py
mbed_tools/build/_internal/config/config.py
mbed_tools/build/_internal/config/source.py
mbed_tools/build/_internal/templates/__init__.py
mbed_tools/build/_internal/templates/mbed_config.tmpl
mbed_tools/cli/__init__.py
mbed_tools/cli/build.py
mbed_tools/cli/configure.py
mbed_tools/cli/list_connected_devices.py
mbed_tools/cli/main.py
mbed_tools/cli/project_management.py
mbed_tools/cli/sterm.py
mbed_tools/devices/__init__.py
mbed_tools/devices/device.py
mbed_tools/devices/devices.py
mbed_tools/devices/exceptions.py
mbed_tools/devices/_internal/__init__.py
mbed_tools/devices/_internal/base_detector.py
mbed_tools/devices/_internal/candidate_device.py
mbed_tools/devices/_internal/detect_candidate_devices.py
mbed_tools/devices/_internal/exceptions.py
mbed_tools/devices/_internal/file_parser.py
mbed_tools/devices/_internal/resolve_board.py
mbed_tools/devices/_internal/darwin/__init__.py
mbed_tools/devices/_internal/darwin/device_detector.py
mbed_tools/devices/_internal/darwin/diskutil.py
mbed_tools/devices/_internal/darwin/ioreg.py
mbed_tools/devices/_internal/darwin/system_profiler.py
mbed_tools/devices/_internal/linux/__init__.py
mbed_tools/devices/_internal/linux/device_detector.py
mbed_tools/devices/_internal/windows/__init__.py
mbed_tools/devices/_internal/windows/component_descriptor.py
mbed_tools/devices/_internal/windows/component_descriptor_utils.py
mbed_tools/devices/_internal/windows/device_detector.py
mbed_tools/devices/_internal/windows/device_instance_id.py
mbed_tools/devices/_internal/windows/disk_aggregation.py
mbed_tools-7.59.0.dist-info/LICENSE
mbed_tools-7.59.0.dist-info/METADATA
mbed_tools-7.59.0.dist-info/WHEEL
mbed_tools-7.59.0.dist-info/entry_points.txt
mbed_tools-7.59.0.dist-info/top_level.txt
mbed_tools-7.59.0.dist-info/RECORD
