Metadata-Version: 2.1
Name: mbed-tools
Version: 7.59.0
Summary: Command line interface for Mbed OS.
Home-page: https://github.com/ARMmbed/mbed-tools
Author: Mbed team
Author-email: support@mbed.com
License: Apache 2.0
Keywords: Arm Mbed OS MbedOS cli command line tools
Classifier: Development Status :: 4 - Beta
Classifier: Intended Audience :: Developers
Classifier: License :: OSI Approved :: Apache Software License
Classifier: Programming Language :: Python
Classifier: Programming Language :: Python :: 3 :: Only
Classifier: Programming Language :: Python :: 3.6
Classifier: Programming Language :: Python :: 3.7
Classifier: Programming Language :: Python :: 3.8
Classifier: Programming Language :: Python :: 3.9
Classifier: Topic :: Software Development :: Build Tools
Classifier: Topic :: Software Development :: Embedded Systems
Requires-Python: >=3.6,<4
License-File: LICENSE
Requires-Dist: python-dotenv
Requires-Dist: Click (<9,>=7.1)
Requires-Dist: GitPython
Requires-Dist: tqdm
Requires-Dist: tabulate
Requires-Dist: requests (>=2.20)
Requires-Dist: typing-extensions
Requires-Dist: Jinja2
Requires-Dist: pyserial
Requires-Dist: psutil ; platform_system == "Linux"
Requires-Dist: pyudev ; platform_system == "Linux"
Requires-Dist: pywin32 ; platform_system == "Windows"
Requires-Dist: dataclasses ; python_version < "3.7"
